sayna_client/__init__.py
sayna_client/client.py
sayna_client/errors.py
sayna_client/http_client.py
sayna_client/types.py
sayna_client/webhook_receiver.py
sayna_client-0.0.13.dist-info/METADATA
sayna_client-0.0.13.dist-info/WHEEL
sayna_client-0.0.13.dist-info/top_level.txt
sayna_client-0.0.13.dist-info/RECORD
