Metadata-Version: 2.4
Name: sayna-client
Version: 0.0.13
Summary: Python SDK for Sayna server-side WebSocket connections
Author: Sayna Team
License: MIT
Project-URL: Homepage, https://github.com/SaynaAi/saysdk
Project-URL: Repository, https://github.com/SaynaAi/saysdk
Project-URL: Documentation, https://github.com/SaynaAi/saysdk/tree/main/python-sdk
Project-URL: Issues, https://github.com/SaynaAi/saysdk/issues
Keywords: sayna,websocket,sdk,server,real-time
Classifier: Development Status :: 3 - Alpha
Classifier: Intended Audience :: Developers
Classifier: License :: OSI Approved :: MIT License
Classifier: Operating System :: OS Independent
Classifier: Programming Language :: Python :: 3
Classifier: Programming Language :: Python :: 3.9
Classifier: Programming Language :: Python :: 3.10
Classifier: Programming Language :: Python :: 3.11
Classifier: Programming Language :: Python :: 3.12
Classifier: Programming Language :: Python :: 3.13
Classifier: Topic :: Software Development :: Libraries :: Python Modules
Classifier: Topic :: Communications
Classifier: Framework :: AsyncIO
Classifier: Typing :: Typed
Requires-Python: >=3.9
Requires-Dist: aiohttp>=3.9.0
Requires-Dist: pydantic>=2.0.0
Provides-Extra: dev
Requires-Dist: pytest>=8.0.0; extra == "dev"
Requires-Dist: pytest-asyncio>=0.23.0; extra == "dev"
Requires-Dist: pytest-cov>=4.1.0; extra == "dev"
Requires-Dist: mypy>=1.8.0; extra == "dev"
Requires-Dist: ruff>=0.6.0; extra == "dev"
